scenery/MetadataTools.py
scenery/Options.py
scenery/Scenery.py
scenery/TitleFetcher.py
scenery/__init__.py
scenery/__main__.py
scenery/model/SceneFile.py
scenery/model/SceneFileMetadata.py
scenery/model/SceneFileMetadataCache.py
scenery/model/__init__.py
scenery-1.0.1.dist-info/METADATA
scenery-1.0.1.dist-info/WHEEL
scenery-1.0.1.dist-info/entry_points.txt
scenery-1.0.1.dist-info/namespace_packages.txt
scenery-1.0.1.dist-info/top_level.txt
scenery-1.0.1.dist-info/zip-safe
scenery-1.0.1.dist-info/RECORD
